mozversion/__init__.py
mozversion/errors.py
mozversion/mozversion.py
mozversion-2.2.0.dist-info/METADATA
mozversion-2.2.0.dist-info/WHEEL
mozversion-2.2.0.dist-info/entry_points.txt
mozversion-2.2.0.dist-info/top_level.txt
mozversion-2.2.0.dist-info/RECORD
